probe_data_process-0.1.6-nspkg.pth
probe_data_process-0.1.6.dist-info/entry_points.txt
probe_data_process-0.1.6.dist-info/namespace_packages.txt
probe_data_process-0.1.6.dist-info/DESCRIPTION.rst
probe_data_process-0.1.6.dist-info/WHEEL
probe_data_process-0.1.6.dist-info/metadata.json
probe_data_process-0.1.6.dist-info/top_level.txt
probe_data_process-0.1.6.dist-info/pbr.json
probe_data_process-0.1.6.dist-info/RECORD
probe_data_process-0.1.6.dist-info/METADATA
probe_data_process-0.1.6.dist-info/zip-safe
probe/data_process/sim_hist.py
probe/data_process/sim_process.py
probe/data_process/sim_manager.py
probe/data_process/sim_common.py
probe/data_process/__init__.py
