Metadata-Version: 2.0
Name: probe-data-process
Version: 0.1.6
Summary: process simulation results
Home-page: UNKNOWN
Author: Petr Zikan
Author-email: zikan.p@gmail.com
License: GPLv3
Platform: UNKNOWN
